cp2k_helper/__init__.py
cp2k_helper/__main__.py
cp2k_helper/_version.py
cp2k_helper/cp2k_helper.py
cp2k_helper-0.0.5.dist-info/LICENSE
cp2k_helper-0.0.5.dist-info/METADATA
cp2k_helper-0.0.5.dist-info/WHEEL
cp2k_helper-0.0.5.dist-info/entry_points.txt
cp2k_helper-0.0.5.dist-info/top_level.txt
cp2k_helper-0.0.5.dist-info/RECORD
