Metadata-Version: 2.1
Name: cp2k-helper
Version: 0.0.5
Summary: A package to help accelerate working with cp2k
Home-page: https://github.com/loevlie/cp2k_helper
Author: Dennis Loevlie
Requires-Python: >=3.5
License-File: LICENSE
Requires-Dist: matplotlib
Requires-Dist: numpy (>=1.17.2)
Requires-Dist: pillow
Requires-Dist: ase (>=3.17.0)
Requires-Dist: seaborn
Requires-Dist: pandas
